trulens/feedback/__init__.py
trulens/feedback/computer.py
trulens/feedback/dummy/__init__.py
trulens/feedback/dummy/endpoint.py
trulens/feedback/dummy/provider.py
trulens/feedback/embeddings.py
trulens/feedback/feedback.py
trulens/feedback/generated.py
trulens/feedback/groundtruth.py
trulens/feedback/llm_provider.py
trulens/feedback/output_schemas.py
trulens/feedback/prompts.py
trulens/feedback/py.typed
trulens/feedback/v2/__init__.py
trulens/feedback/v2/feedback.py
trulens/feedback/v2/provider/__init__.py
trulens/feedback/v2/provider/base.py
trulens_feedback-2.5.3.dist-info/METADATA
trulens_feedback-2.5.3.dist-info/WHEEL
trulens_feedback-2.5.3.dist-info/RECORD
