Metadata-Version: 2.1
Name: trulens-feedback
Version: 2.5.3
Summary: A TruLens extension package implementing feedback functions for LLM App evaluation.
Home-page: https://trulens.org/
License: MIT
Author: Snowflake Inc.
Author-email: ml-observability-wg-dl@snowflake.com
Requires-Python: >=3.9,<4.0
Classifier: Development Status :: 3 - Alpha
Classifier: License :: OSI Approved :: MIT License
Classifier: Operating System :: OS Independent
Classifier: Programming Language :: Python :: 3
Classifier: Programming Language :: Python :: 3.9
Classifier: Programming Language :: Python :: 3.10
Classifier: Programming Language :: Python :: 3.11
Classifier: Programming Language :: Python :: 3.12
Requires-Dist: nltk (>=3.9.1,<4.0.0)
Requires-Dist: numpy (>=1.23.0)
Requires-Dist: pydantic (>=2.4.2,<3.0.0)
Requires-Dist: requests (>=2.31,<3.0)
Requires-Dist: scikit-learn (>=1.3.0,<2.0.0)
Requires-Dist: scipy (>=1.11.1,<2.0.0)
Requires-Dist: trulens-core (>=2.0.0,<3.0.0)
Project-URL: Documentation, https://trulens.org/getting_started/
Project-URL: Repository, https://github.com/truera/trulens
